LICENSE-2.0.txt
MANIFEST.in
NOTICE
README-python.rst
README.rst
setup.cfg
setup.py
bllipparser.egg-info/PKG-INFO
bllipparser.egg-info/SOURCES.txt
bllipparser.egg-info/dependency_links.txt
bllipparser.egg-info/requires.txt
bllipparser.egg-info/top_level.txt
first-stage/PARSE/AnsHeap.h
first-stage/PARSE/AnswerTree.h
first-stage/PARSE/Bchart.C
first-stage/PARSE/Bchart.h
first-stage/PARSE/BchartSm.C
first-stage/PARSE/Bst.C
first-stage/PARSE/Bst.h
first-stage/PARSE/ChartBase.C
first-stage/PARSE/ChartBase.h
first-stage/PARSE/ClassRule.C
first-stage/PARSE/ClassRule.h
first-stage/PARSE/CntxArray.C
first-stage/PARSE/CntxArray.h
first-stage/PARSE/CombineBests.h
first-stage/PARSE/ECArgs.C
first-stage/PARSE/ECArgs.h
first-stage/PARSE/ECString.h
first-stage/PARSE/Edge.C
first-stage/PARSE/Edge.h
first-stage/PARSE/EdgeHeap.C
first-stage/PARSE/EdgeHeap.h
first-stage/PARSE/ExtPos.C
first-stage/PARSE/ExtPos.h
first-stage/PARSE/FBinaryArray.C
first-stage/PARSE/FBinaryArray.h
first-stage/PARSE/Feat.C
first-stage/PARSE/Feat.h
first-stage/PARSE/Feature.C
first-stage/PARSE/Feature.h
first-stage/PARSE/FeatureTree.C
first-stage/PARSE/FeatureTree.h
first-stage/PARSE/Field.C
first-stage/PARSE/Field.h
first-stage/PARSE/FullHist.C
first-stage/PARSE/FullHist.h
first-stage/PARSE/Fusion.C
first-stage/PARSE/Fusion.h
first-stage/PARSE/GotIter.C
first-stage/PARSE/GotIter.h
first-stage/PARSE/InputTree.C
first-stage/PARSE/InputTree.h
first-stage/PARSE/Item.C
first-stage/PARSE/Item.h
first-stage/PARSE/Link.C
first-stage/PARSE/Link.h
first-stage/PARSE/MeChart.C
first-stage/PARSE/MeChart.h
first-stage/PARSE/Params.C
first-stage/PARSE/Params.h
first-stage/PARSE/ParseStats.C
first-stage/PARSE/ParseStats.h
first-stage/PARSE/ReadTree.h
first-stage/PARSE/ScoreTree.C
first-stage/PARSE/ScoreTree.h
first-stage/PARSE/SentRep.C
first-stage/PARSE/SentRep.h
first-stage/PARSE/SimpleAPI.C
first-stage/PARSE/SimpleAPI.h
first-stage/PARSE/Term.C
first-stage/PARSE/Term.h
first-stage/PARSE/TimeIt.C
first-stage/PARSE/TimeIt.h
first-stage/PARSE/UnitRules.C
first-stage/PARSE/UnitRules.h
first-stage/PARSE/ValHeap.C
first-stage/PARSE/ValHeap.h
first-stage/PARSE/Wrd.h
first-stage/PARSE/auxify.h
