Metadata-Version: 1.1
Name: bllipparser
Version: 2016.9.11
Summary: Python bindings for the BLLIP natural language parser
Home-page: http://github.com/BLLIP/bllip-parser
Author: David McClosky
Author-email: notsoweird+pybllipparser@gmail.com
License: Apache 2.0
Keywords: parsing,syntax,linguistics,language,artificial intelligence,machine learning,NLP,natural language,natural language processing,parse,tree
Platform: POSIX
Classifier: Development Status :: 4 - Beta
Classifier: Intended Audience :: Science/Research
Classifier: License :: OSI Approved :: Apache Software License
Classifier: Natural Language :: English
Classifier: Operating System :: POSIX
Classifier: Topic :: Scientific/Engineering :: Artificial Intelligence
